examplepro_2/__init__.py
examplepro_2/exampleprinter.py
examplepro_2-1.0.6.dist-info/LICENSE
examplepro_2-1.0.6.dist-info/METADATA
examplepro_2-1.0.6.dist-info/WHEEL
examplepro_2-1.0.6.dist-info/top_level.txt
examplepro_2-1.0.6.dist-info/RECORD
