Metadata-Version: 2.1
Name: examplepro-2
Version: 1.0.6
Summary: only a test 
Author: Dominik Wut
License: Apache License
License-File: LICENSE
